<object-stream>
  <com.billkuker.rocketry.motorsim.Motor>
    <chamber class="com.billkuker.rocketry.motorsim.CylindricalChamber">
      <ID>30 mm</ID>
      <OD>31 mm</OD>
      <length>200 mm</length>
    </chamber>
    <fuel class="com.billkuker.rocketry.motorsim.fuel.KNSB" serialization="custom">
      <java.net.URI>
        <default>
          <string>motorsim:KNSB</string>
        </default>
      </java.net.URI>
    </fuel>
    <grain class="com.billkuker.rocketry.motorsim.grain.MultiGrain">
      <count>2</count>
      <grain class="com.billkuker.rocketry.motorsim.grain.CoredCylindricalGrain">
        <ID>8 mm</ID>
        <OD>29 mm</OD>
        <aftEndInhibited>false</aftEndInhibited>
        <foreEndInhibited>false</foreEndInhibited>
        <innerSurfaceInhibited>false</innerSurfaceInhibited>
        <length>70 mm</length>
        <outerSurfaceInhibited>true</outerSurfaceInhibited>
      </grain>
      <spacing>5 mm</spacing>
    </grain>
    <name>IOTestMotor</name>
    <nozzle class="com.billkuker.rocketry.motorsim.ConvergentDivergentNozzle">
      <efficiency>0.87</efficiency>
      <exitDiameter>9 mm</exitDiameter>
      <throatDiameter>7.9 mm</throatDiameter>
    </nozzle>
  </com.billkuker.rocketry.motorsim.Motor>
</object-stream>